allauth_2f2a/__init__.py
allauth_2f2a/adapter.py
allauth_2f2a/app_settings.py
allauth_2f2a/forms.py
allauth_2f2a/middleware.py
allauth_2f2a/mixins.py
allauth_2f2a/urls.py
allauth_2f2a/utils.py
allauth_2f2a/views.py
allauth_2f2a/templates/allauth_2f2a/authenticate.html
allauth_2f2a/templates/allauth_2f2a/backup_tokens.html
allauth_2f2a/templates/allauth_2f2a/remove.html
allauth_2f2a/templates/allauth_2f2a/setup.html
django_allauth_2f2a-0.9.1.dist-info/LICENSE
django_allauth_2f2a-0.9.1.dist-info/METADATA
django_allauth_2f2a-0.9.1.dist-info/WHEEL
django_allauth_2f2a-0.9.1.dist-info/top_level.txt
django_allauth_2f2a-0.9.1.dist-info/RECORD
