Metadata-Version: 2.1
Name: django-allauth-2f2a
Version: 0.9.1
Summary: Adds two factor authentication to django-allauth.
Home-page: https://github.com/jeremyagray/django-allauth-2f2a
Author: Jeremy A Gray
Author-email: gray@flyquackswim.com
License: Apache 2.0
Keywords: otp,auth,two factor authentication,allauth,django,2fa
Platform: UNKNOWN
Classifier: Development Status :: 4 - Beta
Classifier: Intended Audience :: Developers
Classifier: Topic :: Software Development :: Libraries :: Python Modules
Classifier: Environment :: Web Environment
Classifier: Topic :: Internet
Classifier: Framework :: Django
Classifier: Framework :: Django :: 2.2
Classifier: Framework :: Django :: 3.2
Classifier: Programming Language :: Python
Classifier: Programming Language :: Python :: 3.6
Classifier: Programming Language :: Python :: 3.7
Classifier: Programming Language :: Python :: 3.8
Classifier: License :: OSI Approved :: Apache Software License
Requires-Python: >=3.6
License-File: LICENSE
Requires-Dist: django (>=2.2)
Requires-Dist: qrcode (>=5.3)
Requires-Dist: django-allauth (>=0.44)
Requires-Dist: django-otp (>=1.0.0)
